{
  "projectName": "프로젝트/프로덕트 관리 프레임워크",
  "createdAt": "2026-03-07T00:00:00.000Z",
  "nodes": [
    {
      "id": "n1",
      "label": "우선순위 획일화 문제",
      "description": "같은 마감일이라도 개인 역량에 따라 체감 난이도가 달라, 일괄적인 우선순위 부여가 맞지 않는 구조적 문제.",
      "category": "문제정의",
      "parentId": null
    },
    {
      "id": "n2",
      "label": "역량별 업무 부하 차이",
      "description": "동일 태스크에 대해 누군가는 여유 있고 누군가는 빠듯한 상황이 발생. 역량 차이를 반영하지 못하는 배분 방식의 한계.",
      "category": "문제정의",
      "parentId": "n1"
    },
    {
      "id": "n6",
      "label": "우수 인력 과부하 딜레마",
      "description": "잘하는 팀원에게 업무가 집중되어 과부하와 이직 리스크가 생기지만, 균등 배분하면 완성도 격차가 심하게 나는 딜레마.",
      "category": "문제정의",
      "parentId": "n2"
    },
    {
      "id": "n8",
      "label": "균등 배분 시 완성도 격차",
      "description": "과부하 방지를 위해 업무를 동등하게 나누면 결과물 퀄리티 차이가 크게 발생하여 프로젝트 품질이 들쑥날쑥해짐.",
      "category": "문제정의",
      "parentId": "n6"
    },
    {
      "id": "n3",
      "label": "역량 파악의 비정량성",
      "description": "회의, 1:1 면담, 완성도 체크로 역량을 파악하지만 정량적/정성적 근거가 부족하여 배분 판단이 주관적이 됨.",
      "category": "문제정의",
      "parentId": null
    },
    {
      "id": "n4",
      "label": "배분 근거 설명 곤란",
      "description": "팀원에게 '왜 이 업무가 나에게?'라는 질문에 뚜렷한 정량적 근거를 제시하기 어려워 PM으로서 곤란한 상황 발생.",
      "category": "문제정의",
      "parentId": "n3"
    },
    {
      "id": "n9",
      "label": "보상 체계 실행 어려움",
      "description": "승진이나 급여 인상으로 보상하고 싶어도 임원진을 설득할 정량적 데이터가 없어 실행이 막히는 상황.",
      "category": "문제정의",
      "parentId": "n3"
    },
    {
      "id": "n23",
      "label": "실시간 피드백 부재",
      "description": "잔디와 스프레드시트를 사용 중이지만 업무 진행 상황에 대한 실시간 피드백이 어려워 상황 파악이 지연됨.",
      "category": "문제정의",
      "parentId": null
    },
    {
      "id": "n10",
      "label": "난이도 × 완성도 스코어링",
      "description": "태스크별 난이도(1~5)를 PM이 사전 부여하고, 완료 시 완성도를 평가하여 팀원별 기여도를 정량화하는 프레임워크.",
      "category": "가설",
      "parentId": "n3"
    },
    {
      "id": "n11",
      "label": "임원 설득용 데이터 생성",
      "description": "스코어링 누적 데이터로 '이 팀원이 난이도 높은 업무를 높은 완성도로 수행했다'는 객관적 근거를 임원에게 제시.",
      "category": "가설",
      "parentId": "n10"
    },
    {
      "id": "n12",
      "label": "배분 투명성 확보",
      "description": "난이도 기반으로 업무를 배분하므로 팀원에게 배분 이유를 설명할 수 있는 정량적 근거가 생김.",
      "category": "가설",
      "parentId": "n10"
    },
    {
      "id": "n13",
      "label": "PM 단독 평가 모델",
      "description": "PM이 실무를 파악하고 있다는 전제 하에, PM 단독 판단의 수치화만으로 충분한 근거가 됨. 복잡한 다면평가 불필요.",
      "category": "가설",
      "parentId": "n10"
    },
    {
      "id": "n26",
      "label": "직군별 난이도 기준표",
      "description": "3개 직군마다 난이도 기준은 다르지만, PM이 모든 직군의 업무를 파악하고 있으므로 통합 판단이 가능.",
      "category": "가설",
      "parentId": "n10"
    },
    {
      "id": "n24",
      "label": "커스텀 관리 툴 개발",
      "description": "업무 관리 + 스코어링 + 실시간 알림/피드백이 통합된 자체 도구. 스프레드시트 검증 후 장기적으로 개발 목표.",
      "category": "가설",
      "parentId": "n23"
    },
    {
      "id": "n14",
      "label": "1개월 파일럿 테스트",
      "description": "한 달간 실제 업무에 난이도/완성도 스코어링을 적용하여 데이터 축적 가능성과 운영 실효성을 검증.",
      "category": "검증",
      "parentId": "n13"
    },
    {
      "id": "n15",
      "label": "프로젝트 1사이클 데이터 확보",
      "description": "임원 설득을 위해서는 프로젝트 한 바퀴(기획~배포) 이상의 누적 데이터가 필요. 파일럿 이후 본격 데이터 수집.",
      "category": "검증",
      "parentId": "n14"
    },
    {
      "id": "n16",
      "label": "과부하 수치 감지 지표",
      "description": "특정 팀원의 난이도×건수 총합이 임계치를 넘으면 과부하로 판단하는 정량 기준. 핵심 성공 지표.",
      "category": "검증",
      "parentId": "n14"
    },
    {
      "id": "n17",
      "label": "데이터 기반 보상 요청",
      "description": "과부하 감지 데이터를 근거로 임원에게 해당 팀원의 보상(승진/급여)을 정량적으로 요청할 수 있게 됨.",
      "category": "개선",
      "parentId": "n16"
    },
    {
      "id": "n18",
      "label": "보상→동기부여→효율 상승",
      "description": "적절한 보상이 주어지면 과부하 속에서도 업무 효율을 유지/향상할 수 있다는 선순환 사이클.",
      "category": "개선",
      "parentId": "n17"
    },
    {
      "id": "n19",
      "label": "반강제 도입 + 리더십 설득",
      "description": "팀원 반발 시 타협보다는 리더십으로 설득하며 도입 추진. 과도한 타협이 오히려 팀 관리를 악화시킬 수 있음.",
      "category": "개선",
      "parentId": "n16"
    },
    {
      "id": "n21",
      "label": "임원 설득 전략 수립",
      "description": "데이터 제시 방식, 타이밍, 인력 이탈 비용 대비 보상 비용 비교 등 임원 설득 전략을 사전에 준비.",
      "category": "개선",
      "parentId": "n17"
    },
    {
      "id": "n25",
      "label": "8인 팀, 3개 직군",
      "description": "PM 1명 포함 8명 규모. 3개 직군으로 구성된 소규모 팀. 직군별 업무 특성과 난이도 기준이 상이.",
      "category": "사용자",
      "parentId": null
    },
    {
      "id": "n27",
      "label": "팀 내부 전용 도구",
      "description": "외부 확장 없이 현재 팀(8명, 3직군)의 내부 운영에 특화된 프레임워크. 범용성보다 실용성 우선.",
      "category": "사용자",
      "parentId": "n25"
    },
    {
      "id": "n5",
      "label": "팀원 간 불만 발생",
      "description": "업무 배분 근거가 불투명하면 형평성에 대한 불만이 발생할 수 있음. 스코어링으로 완화 가능.",
      "category": "위험요소",
      "parentId": null
    },
    {
      "id": "n7",
      "label": "핵심 인력 이탈 리스크",
      "description": "우수 팀원에 대한 지속적 과부하가 이직 결심의 계기가 될 수 있음. 보상 체계가 없으면 리스크 증가.",
      "category": "위험요소",
      "parentId": null
    },
    {
      "id": "n20",
      "label": "임원 보상 거부 리스크",
      "description": "정량 데이터를 제시해도 임원이 보상을 승인하지 않으면 핵심 인력 이탈로 이어질 수 있는 구조적 한계.",
      "category": "위험요소",
      "parentId": "n7"
    },
    {
      "id": "n22",
      "label": "잔디 + 스프레드시트",
      "description": "현재 팀의 업무 관리 도구. 실시간 피드백이 어렵다는 한계가 있지만 당장 대안이 없어 유지.",
      "category": "기술",
      "parentId": null
    }
  ]
}
